whatcha_readin/__init__.py
whatcha_readin/cli.py
whatcha_readin/config.py
whatcha_readin/goodreads.py
whatcha_readin/paths.py
whatcha_readin/utils.py
whatcha_readin/resources/__init__.py
whatcha_readin/resources/commit_msg.py
whatcha_readin-0.0.4.dist-info/LICENSE
whatcha_readin-0.0.4.dist-info/METADATA
whatcha_readin-0.0.4.dist-info/WHEEL
whatcha_readin-0.0.4.dist-info/entry_points.txt
whatcha_readin-0.0.4.dist-info/top_level.txt
whatcha_readin-0.0.4.dist-info/RECORD
